ntstatus/__init__.py
ntstatus/_hresult.py
ntstatus/_ntstatus.py
ntstatus/_thirtytwobits.py
ntstatus/_win32error.py
ntstatus/py.typed
ntstatus-2.0.dist-info/METADATA
ntstatus-2.0.dist-info/WHEEL
ntstatus-2.0.dist-info/licenses/LICENSE
ntstatus-2.0.dist-info/RECORD
