Metadata-Version: 2.4
Name: ntstatus
Version: 2.0
Summary: Python enum for NTSTATUS from WinAPI, supporting comparision to both signed and unsigned integers
Project-URL: Homepage, https://github.com/petamas/python-ntstatus
Project-URL: Bug Tracker, https://github.com/petamas/python-ntstatus/issues
Author-email: Tamás PEREGI <petamas@gmail.com>
License-Expression: MIT
License-File: LICENSE
Classifier: License :: OSI Approved :: MIT License
Classifier: Operating System :: MacOS
Classifier: Operating System :: Microsoft :: Windows
Classifier: Operating System :: OS Independent
Classifier: Operating System :: POSIX
Classifier: Programming Language :: Python :: 3
Classifier: Programming Language :: Python :: 3.10
Classifier: Programming Language :: Python :: 3.11
Classifier: Programming Language :: Python :: 3.12
Classifier: Programming Language :: Python :: 3.13
Requires-Python: >=3.10
